{
	"id": 24573940,
	"node_id": "MDEwOlJlcG9zaXRvcnkyNDU3Mzk0MA==",
	"name": "VENTouchLock",
	"full_name": "venmo/VENTouchLock",
	"owner": {
		"login": "venmo",
		"id": 256998,
		"node_id": "MDEyOk9yZ2FuaXphdGlvbjI1Njk5OA==",
		"avatar_url": "https://avatars0.githubusercontent.com/u/256998?v=4",
		"gravatar_id": "",
		"url": "https://api.github.com/users/venmo",
		"html_url": "https://github.com/venmo",
		"followers_url": "https://api.github.com/users/venmo/followers",
		"following_url": "https://api.github.com/users/venmo/following{/other_user}",
		"gists_url": "https://api.github.com/users/venmo/gists{/gist_id}",
		"starred_url": "https://api.github.com/users/venmo/starred{/owner}{/repo}",
		"subscriptions_url": "https://api.github.com/users/venmo/subscriptions",
		"organizations_url": "https://api.github.com/users/venmo/orgs",
		"repos_url": "https://api.github.com/users/venmo/repos",
		"events_url": "https://api.github.com/users/venmo/events{/privacy}",
		"received_events_url": "https://api.github.com/users/venmo/received_events",
		"type": "Organization",
		"site_admin": false
	},
	"private": false,
	"html_url": "https://github.com/venmo/VENTouchLock",
	"description": "A Touch ID and Passcode framework used in the Venmo app.",
	"fork": false,
	"url": "https://api.github.com/repos/venmo/VENTouchLock",
	"forks_url": "https://api.github.com/repos/venmo/VENTouchLock/forks",
	"keys_url": "https://api.github.com/repos/venmo/VENTouchLock/keys{/key_id}",
	"collaborators_url": "https://api.github.com/repos/venmo/VENTouchLock/collaborators{/collaborator}",
	"teams_url": "https://api.github.com/repos/venmo/VENTouchLock/teams",
	"hooks_url": "https://api.github.com/repos/venmo/VENTouchLock/hooks",
	"issue_events_url": "https://api.github.com/repos/venmo/VENTouchLock/issues/events{/number}",
	"events_url": "https://api.github.com/repos/venmo/VENTouchLock/events",
	"assignees_url": "https://api.github.com/repos/venmo/VENTouchLock/assignees{/user}",
	"branches_url": "https://api.github.com/repos/venmo/VENTouchLock/branches{/branch}",
	"tags_url": "https://api.github.com/repos/venmo/VENTouchLock/tags",
	"blobs_url": "https://api.github.com/repos/venmo/VENTouchLock/git/blobs{/sha}",
	"git_tags_url": "https://api.github.com/repos/venmo/VENTouchLock/git/tags{/sha}",
	"git_refs_url": "https://api.github.com/repos/venmo/VENTouchLock/git/refs{/sha}",
	"trees_url": "https://api.github.com/repos/venmo/VENTouchLock/git/trees{/sha}",
	"statuses_url": "https://api.github.com/repos/venmo/VENTouchLock/statuses/{sha}",
	"languages_url": "https://api.github.com/repos/venmo/VENTouchLock/languages",
	"stargazers_url": "https://api.github.com/repos/venmo/VENTouchLock/stargazers",
	"contributors_url": "https://api.github.com/repos/venmo/VENTouchLock/contributors",
	"subscribers_url": "https://api.github.com/repos/venmo/VENTouchLock/subscribers",
	"subscription_url": "https://api.github.com/repos/venmo/VENTouchLock/subscription",
	"commits_url": "https://api.github.com/repos/venmo/VENTouchLock/commits{/sha}",
	"git_commits_url": "https://api.github.com/repos/venmo/VENTouchLock/git/commits{/sha}",
	"comments_url": "https://api.github.com/repos/venmo/VENTouchLock/comments{/number}",
	"issue_comment_url": "https://api.github.com/repos/venmo/VENTouchLock/issues/comments{/number}",
	"contents_url": "https://api.github.com/repos/venmo/VENTouchLock/contents/{+path}",
	"compare_url": "https://api.github.com/repos/venmo/VENTouchLock/compare/{base}...{head}",
	"merges_url": "https://api.github.com/repos/venmo/VENTouchLock/merges",
	"archive_url": "https://api.github.com/repos/venmo/VENTouchLock/{archive_format}{/ref}",
	"downloads_url": "https://api.github.com/repos/venmo/VENTouchLock/downloads",
	"issues_url": "https://api.github.com/repos/venmo/VENTouchLock/issues{/number}",
	"pulls_url": "https://api.github.com/repos/venmo/VENTouchLock/pulls{/number}",
	"milestones_url": "https://api.github.com/repos/venmo/VENTouchLock/milestones{/number}",
	"notifications_url": "https://api.github.com/repos/venmo/VENTouchLock/notifications{?since,all,participating}",
	"labels_url": "https://api.github.com/repos/venmo/VENTouchLock/labels{/name}",
	"releases_url": "https://api.github.com/repos/venmo/VENTouchLock/releases{/id}",
	"deployments_url": "https://api.github.com/repos/venmo/VENTouchLock/deployments",
	"created_at": "2014-09-29T00:07:22Z",
	"updated_at": "2018-07-02T08:01:14Z",
	"pushed_at": "2017-08-21T12:42:33Z",
	"git_url": "git://github.com/venmo/VENTouchLock.git",
	"ssh_url": "git@github.com:venmo/VENTouchLock.git",
	"clone_url": "https://github.com/venmo/VENTouchLock.git",
	"svn_url": "https://github.com/venmo/VENTouchLock",
	"homepage": null,
	"size": 3477,
	"stargazers_count": 1000,
	"watchers_count": 1000,
	"language": "Objective-C",
	"has_issues": true,
	"has_projects": true,
	"has_downloads": true,
	"has_wiki": true,
	"has_pages": false,
	"forks_count": 129,
	"mirror_url": null,
	"archived": false,
	"open_issues_count": 16,
	"license": {
		"key": "mit",
		"name": "MIT License",
		"spdx_id": "MIT",
		"url": "https://api.github.com/licenses/mit",
		"node_id": "MDc6TGljZW5zZTEz"
	},
	"forks": 129,
	"open_issues": 16,
	"watchers": 1000,
	"default_branch": "master",
	"permissions": {
		"admin": false,
		"push": false,
		"pull": true
	},
	"organization": {
		"login": "venmo",
		"id": 256998,
		"node_id": "MDEyOk9yZ2FuaXphdGlvbjI1Njk5OA==",
		"avatar_url": "https://avatars0.githubusercontent.com/u/256998?v=4",
		"gravatar_id": "",
		"url": "https://api.github.com/users/venmo",
		"html_url": "https://github.com/venmo",
		"followers_url": "https://api.github.com/users/venmo/followers",
		"following_url": "https://api.github.com/users/venmo/following{/other_user}",
		"gists_url": "https://api.github.com/users/venmo/gists{/gist_id}",
		"starred_url": "https://api.github.com/users/venmo/starred{/owner}{/repo}",
		"subscriptions_url": "https://api.github.com/users/venmo/subscriptions",
		"organizations_url": "https://api.github.com/users/venmo/orgs",
		"repos_url": "https://api.github.com/users/venmo/repos",
		"events_url": "https://api.github.com/users/venmo/events{/privacy}",
		"received_events_url": "https://api.github.com/users/venmo/received_events",
		"type": "Organization",
		"site_admin": false
	},
	"network_count": 129,
	"subscribers_count": 66
}