{
	"id": 11960085,
	"node_id": "MDEwOlJlcG9zaXRvcnkxMTk2MDA4NQ==",
	"name": "headroom.js",
	"full_name": "WickyNilliams/headroom.js",
	"owner": {
		"login": "WickyNilliams",
		"id": 1091390,
		"node_id": "MDQ6VXNlcjEwOTEzOTA=",
		"avatar_url": "https://avatars3.githubusercontent.com/u/1091390?v=4",
		"gravatar_id": "",
		"url": "https://api.github.com/users/WickyNilliams",
		"html_url": "https://github.com/WickyNilliams",
		"followers_url": "https://api.github.com/users/WickyNilliams/followers",
		"following_url": "https://api.github.com/users/WickyNilliams/following{/other_user}",
		"gists_url": "https://api.github.com/users/WickyNilliams/gists{/gist_id}",
		"starred_url": "https://api.github.com/users/WickyNilliams/starred{/owner}{/repo}",
		"subscriptions_url": "https://api.github.com/users/WickyNilliams/subscriptions",
		"organizations_url": "https://api.github.com/users/WickyNilliams/orgs",
		"repos_url": "https://api.github.com/users/WickyNilliams/repos",
		"events_url": "https://api.github.com/users/WickyNilliams/events{/privacy}",
		"received_events_url": "https://api.github.com/users/WickyNilliams/received_events",
		"type": "User",
		"site_admin": false
	},
	"private": false,
	"html_url": "https://github.com/WickyNilliams/headroom.js",
	"description": "Give your pages some headroom. Hide your header until you need it",
	"fork": false,
	"url": "https://api.github.com/repos/WickyNilliams/headroom.js",
	"forks_url": "https://api.github.com/repos/WickyNilliams/headroom.js/forks",
	"keys_url": "https://api.github.com/repos/WickyNilliams/headroom.js/keys{/key_id}",
	"collaborators_url": "https://api.github.com/repos/WickyNilliams/headroom.js/collaborators{/collaborator}",
	"teams_url": "https://api.github.com/repos/WickyNilliams/headroom.js/teams",
	"hooks_url": "https://api.github.com/repos/WickyNilliams/headroom.js/hooks",
	"issue_events_url": "https://api.github.com/repos/WickyNilliams/headroom.js/issues/events{/number}",
	"events_url": "https://api.github.com/repos/WickyNilliams/headroom.js/events",
	"assignees_url": "https://api.github.com/repos/WickyNilliams/headroom.js/assignees{/user}",
	"branches_url": "https://api.github.com/repos/WickyNilliams/headroom.js/branches{/branch}",
	"tags_url": "https://api.github.com/repos/WickyNilliams/headroom.js/tags",
	"blobs_url": "https://api.github.com/repos/WickyNilliams/headroom.js/git/blobs{/sha}",
	"git_tags_url": "https://api.github.com/repos/WickyNilliams/headroom.js/git/tags{/sha}",
	"git_refs_url": "https://api.github.com/repos/WickyNilliams/headroom.js/git/refs{/sha}",
	"trees_url": "https://api.github.com/repos/WickyNilliams/headroom.js/git/trees{/sha}",
	"statuses_url": "https://api.github.com/repos/WickyNilliams/headroom.js/statuses/{sha}",
	"languages_url": "https://api.github.com/repos/WickyNilliams/headroom.js/languages",
	"stargazers_url": "https://api.github.com/repos/WickyNilliams/headroom.js/stargazers",
	"contributors_url": "https://api.github.com/repos/WickyNilliams/headroom.js/contributors",
	"subscribers_url": "https://api.github.com/repos/WickyNilliams/headroom.js/subscribers",
	"subscription_url": "https://api.github.com/repos/WickyNilliams/headroom.js/subscription",
	"commits_url": "https://api.github.com/repos/WickyNilliams/headroom.js/commits{/sha}",
	"git_commits_url": "https://api.github.com/repos/WickyNilliams/headroom.js/git/commits{/sha}",
	"comments_url": "https://api.github.com/repos/WickyNilliams/headroom.js/comments{/number}",
	"issue_comment_url": "https://api.github.com/repos/WickyNilliams/headroom.js/issues/comments{/number}",
	"contents_url": "https://api.github.com/repos/WickyNilliams/headroom.js/contents/{+path}",
	"compare_url": "https://api.github.com/repos/WickyNilliams/headroom.js/compare/{base}...{head}",
	"merges_url": "https://api.github.com/repos/WickyNilliams/headroom.js/merges",
	"archive_url": "https://api.github.com/repos/WickyNilliams/headroom.js/{archive_format}{/ref}",
	"downloads_url": "https://api.github.com/repos/WickyNilliams/headroom.js/downloads",
	"issues_url": "https://api.github.com/repos/WickyNilliams/headroom.js/issues{/number}",
	"pulls_url": "https://api.github.com/repos/WickyNilliams/headroom.js/pulls{/number}",
	"milestones_url": "https://api.github.com/repos/WickyNilliams/headroom.js/milestones{/number}",
	"notifications_url": "https://api.github.com/repos/WickyNilliams/headroom.js/notifications{?since,all,participating}",
	"labels_url": "https://api.github.com/repos/WickyNilliams/headroom.js/labels{/name}",
	"releases_url": "https://api.github.com/repos/WickyNilliams/headroom.js/releases{/id}",
	"deployments_url": "https://api.github.com/repos/WickyNilliams/headroom.js/deployments",
	"created_at": "2013-08-07T20:42:58Z",
	"updated_at": "2018-07-04T20:53:40Z",
	"pushed_at": "2018-02-21T01:36:16Z",
	"git_url": "git://github.com/WickyNilliams/headroom.js.git",
	"ssh_url": "git@github.com:WickyNilliams/headroom.js.git",
	"clone_url": "https://github.com/WickyNilliams/headroom.js.git",
	"svn_url": "https://github.com/WickyNilliams/headroom.js",
	"homepage": "http://wicky.nillia.ms/headroom.js/",
	"size": 402,
	"stargazers_count": 9859,
	"watchers_count": 9859,
	"language": "JavaScript",
	"has_issues": true,
	"has_projects": true,
	"has_downloads": true,
	"has_wiki": true,
	"has_pages": true,
	"forks_count": 842,
	"mirror_url": null,
	"archived": false,
	"open_issues_count": 34,
	"license": {
		"key": "mit",
		"name": "MIT License",
		"spdx_id": "MIT",
		"url": "https://api.github.com/licenses/mit",
		"node_id": "MDc6TGljZW5zZTEz"
	},
	"forks": 842,
	"open_issues": 34,
	"watchers": 9859,
	"default_branch": "master",
	"permissions": {
		"admin": false,
		"push": false,
		"pull": true
	},
	"network_count": 842,
	"subscribers_count": 226
}