{
	"id": 54346799,
	"node_id": "MDEwOlJlcG9zaXRvcnk1NDM0Njc5OQ==",
	"name": "public-apis",
	"full_name": "toddmotto/public-apis",
	"owner": {
		"login": "toddmotto",
		"id": 1655968,
		"node_id": "MDQ6VXNlcjE2NTU5Njg=",
		"avatar_url": "https://avatars0.githubusercontent.com/u/1655968?v=4",
		"gravatar_id": "",
		"url": "https://api.github.com/users/toddmotto",
		"html_url": "https://github.com/toddmotto",
		"followers_url": "https://api.github.com/users/toddmotto/followers",
		"following_url": "https://api.github.com/users/toddmotto/following{/other_user}",
		"gists_url": "https://api.github.com/users/toddmotto/gists{/gist_id}",
		"starred_url": "https://api.github.com/users/toddmotto/starred{/owner}{/repo}",
		"subscriptions_url": "https://api.github.com/users/toddmotto/subscriptions",
		"organizations_url": "https://api.github.com/users/toddmotto/orgs",
		"repos_url": "https://api.github.com/users/toddmotto/repos",
		"events_url": "https://api.github.com/users/toddmotto/events{/privacy}",
		"received_events_url": "https://api.github.com/users/toddmotto/received_events",
		"type": "User",
		"site_admin": false
	},
	"private": false,
	"html_url": "https://github.com/toddmotto/public-apis",
	"description": "A collective list of public JSON APIs for use in web development.",
	"fork": false,
	"url": "https://api.github.com/repos/toddmotto/public-apis",
	"forks_url": "https://api.github.com/repos/toddmotto/public-apis/forks",
	"keys_url": "https://api.github.com/repos/toddmotto/public-apis/keys{/key_id}",
	"collaborators_url": "https://api.github.com/repos/toddmotto/public-apis/collaborators{/collaborator}",
	"teams_url": "https://api.github.com/repos/toddmotto/public-apis/teams",
	"hooks_url": "https://api.github.com/repos/toddmotto/public-apis/hooks",
	"issue_events_url": "https://api.github.com/repos/toddmotto/public-apis/issues/events{/number}",
	"events_url": "https://api.github.com/repos/toddmotto/public-apis/events",
	"assignees_url": "https://api.github.com/repos/toddmotto/public-apis/assignees{/user}",
	"branches_url": "https://api.github.com/repos/toddmotto/public-apis/branches{/branch}",
	"tags_url": "https://api.github.com/repos/toddmotto/public-apis/tags",
	"blobs_url": "https://api.github.com/repos/toddmotto/public-apis/git/blobs{/sha}",
	"git_tags_url": "https://api.github.com/repos/toddmotto/public-apis/git/tags{/sha}",
	"git_refs_url": "https://api.github.com/repos/toddmotto/public-apis/git/refs{/sha}",
	"trees_url": "https://api.github.com/repos/toddmotto/public-apis/git/trees{/sha}",
	"statuses_url": "https://api.github.com/repos/toddmotto/public-apis/statuses/{sha}",
	"languages_url": "https://api.github.com/repos/toddmotto/public-apis/languages",
	"stargazers_url": "https://api.github.com/repos/toddmotto/public-apis/stargazers",
	"contributors_url": "https://api.github.com/repos/toddmotto/public-apis/contributors",
	"subscribers_url": "https://api.github.com/repos/toddmotto/public-apis/subscribers",
	"subscription_url": "https://api.github.com/repos/toddmotto/public-apis/subscription",
	"commits_url": "https://api.github.com/repos/toddmotto/public-apis/commits{/sha}",
	"git_commits_url": "https://api.github.com/repos/toddmotto/public-apis/git/commits{/sha}",
	"comments_url": "https://api.github.com/repos/toddmotto/public-apis/comments{/number}",
	"issue_comment_url": "https://api.github.com/repos/toddmotto/public-apis/issues/comments{/number}",
	"contents_url": "https://api.github.com/repos/toddmotto/public-apis/contents/{+path}",
	"compare_url": "https://api.github.com/repos/toddmotto/public-apis/compare/{base}...{head}",
	"merges_url": "https://api.github.com/repos/toddmotto/public-apis/merges",
	"archive_url": "https://api.github.com/repos/toddmotto/public-apis/{archive_format}{/ref}",
	"downloads_url": "https://api.github.com/repos/toddmotto/public-apis/downloads",
	"issues_url": "https://api.github.com/repos/toddmotto/public-apis/issues{/number}",
	"pulls_url": "https://api.github.com/repos/toddmotto/public-apis/pulls{/number}",
	"milestones_url": "https://api.github.com/repos/toddmotto/public-apis/milestones{/number}",
	"notifications_url": "https://api.github.com/repos/toddmotto/public-apis/notifications{?since,all,participating}",
	"labels_url": "https://api.github.com/repos/toddmotto/public-apis/labels{/name}",
	"releases_url": "https://api.github.com/repos/toddmotto/public-apis/releases{/id}",
	"deployments_url": "https://api.github.com/repos/toddmotto/public-apis/deployments",
	"created_at": "2016-03-20T23:49:42Z",
	"updated_at": "2018-07-05T16:18:59Z",
	"pushed_at": "2018-07-05T04:19:24Z",
	"git_url": "git://github.com/toddmotto/public-apis.git",
	"ssh_url": "git@github.com:toddmotto/public-apis.git",
	"clone_url": "https://github.com/toddmotto/public-apis.git",
	"svn_url": "https://github.com/toddmotto/public-apis",
	"homepage": "https://toddmotto.com",
	"size": 2140,
	"stargazers_count": 39133,
	"watchers_count": 39133,
	"language": "Python",
	"has_issues": true,
	"has_projects": true,
	"has_downloads": true,
	"has_wiki": true,
	"has_pages": false,
	"forks_count": 3840,
	"mirror_url": null,
	"archived": false,
	"open_issues_count": 6,
	"license": null,
	"forks": 3840,
	"open_issues": 6,
	"watchers": 39133,
	"default_branch": "master",
	"permissions": {
		"admin": false,
		"push": false,
		"pull": true
	},
	"network_count": 3840,
	"subscribers_count": 1347
}